{"skeleton":{"hash":"uBNRB9FXhVI","spine":"4.2.36","x":-54.95,"y":-58.35,"width":112,"height":115,"images":"./images/","audio":"./audio"},"bones":[{"name":"root"},{"name":"tran","parent":"root","x":1.55,"y":25.65},{"name":"face","parent":"root","x":1.05,"y":-2.35},{"name":"mieng","parent":"tran","x":-1.5,"y":-47},{"name":"eye","parent":"tran","x":-24,"y":-27.5},{"name":"eye2","parent":"tran","x":19.67,"y":-27.5,"shearX":-179.82}],"slots":[{"name":"Ellipse 14 copy 3","bone":"face","attachment":"Ellipse 14 copy 3"},{"name":"Layer 1","bone":"tran","attachment":"Layer 1"},{"name":"Shape 524","bone":"eye","attachment":"Shape 524"},{"name":"Shape 525","bone":"eye2","attachment":"Shape 524"},{"name":"Shape 520","bone":"mieng","attachment":"Shape 520"}],"skins":[{"name":"default","attachments":{"Ellipse 14 copy 3":{"Ellipse 14 copy 3":{"width":112,"height":112}},"Layer 1":{"Layer 1":{"width":105,"height":62}},"Shape 520":{"Shape 520":{"width":52,"height":18}},"Shape 524":{"Shape 524":{"width":19,"height":19}},"Shape 525":{"Shape 524":{"width":19,"height":19}}}}],"animations":{"animation":{"slots":{"Layer 1":{"rgba":[{"color":"ffffffa5","curve":[0.167,1,0.333,1,0.167,1,0.333,1,0.167,1,0.333,1,0.167,0.65,0.333,1]},{"time":0.5,"color":"ffffffff","curve":[0.778,1,1.056,1,0.778,1,1.056,1,0.778,1,1.056,1,0.778,1,1.056,0.65]},{"time":1.3333,"color":"ffffffa5"}]}},"bones":{"tran":{"translate":[{"curve":[0.167,0,0.333,0,0.167,0,0.333,-2.65]},{"time":0.5,"y":-2.65,"curve":[0.533,0,0.567,-3.89,0.533,-2.65,0.567,-2.65]},{"time":0.6,"x":-3.89,"y":-2.65,"curve":[0.644,-3.89,0.689,4.87,0.644,-2.65,0.689,-2.65]},{"time":0.7333,"x":4.87,"y":-2.65,"curve":[0.778,4.87,0.822,-0.65,0.778,-2.65,0.822,-2.65]},{"time":0.8667,"x":-0.65,"y":-2.65,"curve":[0.911,-0.65,0.956,4.87,0.911,-2.65,0.956,-2.65]},{"time":1,"x":4.87,"y":-2.65,"curve":[1.111,4.87,1.222,0,1.111,-2.65,1.222,0]},{"time":1.3333}],"scale":[{"curve":[0.167,1,0.333,1.039,0.167,1,0.333,0.916]},{"time":0.5,"x":1.039,"y":0.916,"curve":[0.778,1.039,1.056,1,0.778,0.916,1.056,1]},{"time":1.3333}]},"face":{"scale":[{"curve":[0.167,1,0.333,1.02,0.167,1,0.333,0.969]},{"time":0.5,"x":1.02,"y":0.969,"curve":[0.667,1.02,0.833,1,0.667,0.969,0.833,1]},{"time":1}]}}}}}